corgi/__init__.py
corgi/coerce.py
corgi/dictionary.py
corgi/functional.py
corgi/iterate.py
corgi/math.py
corgi/ml.py
corgi/numpy_utils.py
corgi/pandas_utils.py
corgi/sql.py
corgi/stats.py
corgi/visualization.py
corgi/keras/__init__.py
corgi/keras/char.py
corgi/keras/distance.py
corgi/keras/metrics.py
corgi-0.3.2.dist-info/LICENSE
corgi-0.3.2.dist-info/METADATA
corgi-0.3.2.dist-info/WHEEL
corgi-0.3.2.dist-info/top_level.txt
corgi-0.3.2.dist-info/RECORD
