Metadata-Version: 2.1
Name: corgi
Version: 0.3.2
Summary: Python data and analysis tools
Home-page: https://github.com/log0ymxm/corgi
Author: Paul English
Author-email: paulnglsh@gmail.com
License: UNKNOWN
Platform: UNKNOWN
Requires-Dist: numpy
Requires-Dist: six
Requires-Dist: sqlalchemy
Requires-Dist: tqdm
